{
    "About": "Sou",
    "Chat": "Chat",
    "Skills": "Ladrès",
    "Settings": "Anviwònman",
    "Login": "Ouvri sesyon an",
    "Logout": "Dekonekte",
    "Themes": "Themes",
    "Chat Settings": "Chat Anviwònman",
    "ChatApp Settings": "Anviwònman chat",
    "Select Theme": "Chwazi Tèm",
    "Default Theme": "Tèm Default",
    "Light": "Limyè",
    "Dark": "Nwa",
    "Custom": "Custom",
    "Enter As Send": "Mete kòm Voye",
    "Send message by pressing ENTER": "Voye mesaj pa peze ENTER",
    "Mic Settings": "Mic Anviwònman",
    "Mic Input": "Mikwo Antre",
    "Enable mic to give voice input": "Pèmèt MIC bay opinyon vwa",
    "Speech Settings": "Anviwònman Lapawòl",
    "Speech Output": "Pawòl Lapawòl",
    "Enable speech output only for speech input": "Pèmèt pwodiksyon diskou sèlman pou opinyon diskou",
    "Speech Output Always ON": "Pawòl Lapawòl Toujou sou",
    "Enable speech output regardless of input type": "Pèmèt pwodiksyon diskou kèlkeswa kalite opinyon",
    "Speech Output Language": "Lang Sòti Lapawòl",
    "Select Default Language": "Chwazi lang default",
    "Text Language Settings": "Anviwònman tèks tèks",
    "Server Settings": "Anviwònman sèvè",
    "Select backend server for the app": "Chwazi sèvè backend pou app a",
    "Account Settings": "Kont Anviwònman",
    "Change Password": "Chanje modpas",
    "Save": "Sove",
    "Change Server": "Chanje sèvè",
    "Please login again to change SUSI server": "Tanpri konekte ankò pou chanje SUSI sèvè",
    "Text-To-Speech Settings": "Text-to-Speech Settings",
    "General": "Jeneral",
    "Speech Rate": "Pawòl Lapawòl",
    "Speech Pitch": "Pitch lapawòl",
    "Reset Speech Rate": "Reyaksyon Resevwa pousantaj",
    "Reset the speed at which the text is spoken to normal": "Reyaji vitès la nan ki se tèks la pale ak nòmal",
    "Reset Speech Pitch": "Reyaksyon Pitch Pale",
    "Reset the pitch at which the text is spoken to default": "Reyajiste anplasman an nan ki se tèks la pale ak default",
    "Listen to an example": "Koute yon egzanp",
    "Play a short demonstration of speech synthesis": "Jwe yon demonstrasyon kout nan sentèz diskou",
    "Custom URL": "Custom URL",
    "Use Custom Server": "Sèvi ak sèvè Custom",
    "Please enter a valid URL first": "Tanpri antre yon URL ki valab an premye",
    "Theme Changed": "Tèm chanje",
    "Connection Error": "Koneksyon Erè",
    "Please verify that Susi Hardware is running on address you mentioned": "Tanpri verifye ke Susi Materyèl ap kouri sou adrès ou mansyone",
    "Enter a valid Address": "Mete yon adrès ki valab",
    "Enter Socket Web Address": "Mete Adrès Socket entènèt la",
    "Websocket URL": "URL Websocket",
    "Connect": "Konekte",
    "Search": "Search",
    "Type a message...": "Kalite yon mesaj ...",
    "Speak Now": "Pale kounya",
    "Login Failed. Try Again": "Login Echèk. Eseye anko",
    "Some error occurred. Try Again": "Gen kèk erè ki te fèt. Eseye anko",
    "Please check your internet connection": "Tanpri tcheke koneksyon entènèt ou",
    "Enter a valid URL": "Mete yon URL ki valab",
    "Enter a valid Email Address": "Mete yon adrès imèl ki valab",
    "Minimum 6 characters required": "Minimòm 6 karaktè yo mande yo",
    "Login to SUSI": "Login to SUSI",
    "Email": "Imèl",
    "Password": "Modpas",
    "Forgot Password?": "Bliye modpas?",
    "Sign Up": "Enskri",
    "Chat Anonymously": "Chat anonim",
    "OR": "OSWA",
    "Email already taken. Please try with another email.": "Imèl deja pran. Tanpri eseye ak yon lòt imel.",
    "Sign Up with SUSI": "Enskri avèk SUSI",
    "Confirm Password": "Konfime modpas",
    "If you have an Account Please Login": "Si ou gen yon Kont Tanpri Login",
    "Current Password": "Kouran modpas",
    "New Password": "Nouvo modpas",
    "Confirm New Password": "Konfime nouvo modpas",
    "Change": "Chanjman",
    "Worst": "Pi move",
    "Too Insecure": "Twò anksyeu",
    "Bad": "Move",
    "Weak": "Fèb",
    "Good": "Bon",
    "Strong": "Bonjan",
    "Check your password again": "Tcheke modpas ou ankò",
    "Invalid Credentials. Please check your Email or Password.": "Envalid Kredansyèl. Tanpri tcheke Imèl ou oswa Modpas.",
    "Please login again.": "Tanpri konekte ankò.",
    "Please Try Again.": "Tanpri eseye ankò.",
    "Failed. Try Again": "Failed. Eseye anko",
    "Forgot Password ?": "Bliye modpas?",
    "Reset": "Reset",
    "This Field Is Required": "Sa a se jaden obligatwa",
    "Invalid Email": "Envalid Imèl",
    "Email does not exist": "Imèl pa egziste",
    "Cancel": "Anile",
    "Done": "Fè",
    "Change color of": "Chanje koulè nan",
    "Body Background Image URL": "Kò Istorik Imaj URL",
    "Remove URL": "Retire URL",
    "Message Background Image URL": "Mesaj Istorik Imaj URL",
    "Select Server": "Chwazi sèvè",
    "Preferences": "Preferences",
    "Mobile": "Mobile",
    "Expand your experience get closer and stay current": "Ogmante eksperyans ou jwenn pi pre epi rete aktyèl",
    "Add your phone number": "Add nimewo telefòn ou",
    "We will text a verification code to this number. Standard SMS fees may apply.": "Nou pral tèks yon kòd verifikasyon pou nimewo sa a. Creole frè SMS ka aplike.",
    "Save Changes": "Sove chanjman",
    "Account": "Kont",
    "Theme": "Tèm",
    "Your Account": "Kont ou",
    "Your Email": "Adrès elektronik ou",
    "Country/region:": "Peyi / rejyon:",
    "Phone number:": "Nimewo telefòn:",
    "Color of": "Koulè nan",
    "Header": "Header",
    "Message Pane": "Mesaj fenèt",
    "Body": "Kò",
    "Composer": "Konpozitè",
    "Textarea": "Tèks",
    "Button": "Bouton",
    "Change your Account Password": "Chanje Modpas Kont ou",
    "Share about SUSI on Facebook": "Pataje sou SUSI sou Facebook",
    "Share": "Pataje",
    "Tweet about SUSI on Twitter": "Tweet sou SUSI sou Twitter",
    "Share about SUSI on Google+": "Pataje sou SUSI sou Google+"
}
